SNAKES_AND_LADDERS/snakes_and_ladders.py
SNAKES_AND_LADDERS-1.dist-info/LICENSE
SNAKES_AND_LADDERS-1.dist-info/METADATA
SNAKES_AND_LADDERS-1.dist-info/WHEEL
SNAKES_AND_LADDERS-1.dist-info/entry_points.txt
SNAKES_AND_LADDERS-1.dist-info/top_level.txt
SNAKES_AND_LADDERS-1.dist-info/RECORD
