Metadata-Version: 2.1
Name: SNAKES-AND-LADDERS
Version: 1
Summary: This package contains implementation of the game "SNAKES_AND_LADDERS" on command line interface with 100 tiles on the board.
Home-page: https://github.com/GlobalCreativeCommunityFounder/SNAKES_AND_LADDERS
Author: GlobalCreativeCommunityFounder
Author-email: globalcreativecommunityfounder@gmail.com
License: MIT
Platform: UNKNOWN
Classifier: Programming Language :: Python :: 3
Classifier: Programming Language :: Python :: 3.7
